{
  "id": "agile",
  "topics": [
    "software_development"
  ],
  "translations": {
    "en": {
      "term": "Agile",
      "definition": "A flexible software development approach that works in short cycles, regularly reviewing and improving the product."
    },
    "pl": {
      "term": "Agile",
      "definition": "Elastyczne podejście do tworzenia oprogramowania, które działa w krótkich cyklach, regularnie przeglądając i ulepszając produkt."
    },
    "cy": {
      "term": "Agile",
      "definition": "Dull datblygu meddalwedd hyblyg sy'n gweithio mewn cylchoedd byr, gan adolygu a gwella'r cynnyrch yn rheolaidd."
    },
    "ar": {
      "term": "المنهجية الرشيقة",
      "definition": "نهج لتطوير البرمجيات يعمل في دورات قصيرة مع إمكانية التكيف مع التغييرات باستمرار."
    },
    "ro": {
      "term": "Agile",
      "definition": "O abordare a dezvoltării software care lucrează în cicluri scurte, cu posibilitatea de a se adapta la schimbări în mod continuu."
    }
  }
}