{
  "id": "input",
  "topics": [
    "programming"
  ],
  "translations": {
    "en": {
      "term": "Input",
      "definition": "Data entered into a program by a user or another system."
    },
    "pl": {
      "term": "Wejście",
      "definition": "Dane wprowadzane do programu przez użytkownika lub inny system."
    },
    "cy": {
      "term": "Mewnbwn",
      "definition": "Data a gofnodir i mewn i raglen gan ddefnyddiwr neu system arall."
    },
    "ar": {
      "term": "إدخال",
      "definition": "البيانات التي تُدخَل إلى برنامج، عادةً من لوحة المفاتيح أو الملفات أو المستشعرات."
    },
    "ro": {
      "term": "Intrare",
      "definition": "Date introduse într-un program, de obicei de la tastatură, fișiere sau senzori."
    }
  }
}