{
  "id": "rom",
  "topics": [
    "hardware"
  ],
  "translations": {
    "en": {
      "term": "ROM",
      "definition": "Read-Only Memory; permanent storage containing instructions the computer needs to start up."
    },
    "pl": {
      "term": "ROM",
      "definition": "Pamięć tylko do odczytu; trwały magazyn zawierający instrukcje potrzebne komputerowi do uruchomienia."
    },
    "cy": {
      "term": "ROM",
      "definition": "Cof Darllen yn Unig; storfa barhaol sy'n cynnwys cyfarwyddiadau sydd eu hangen ar y cyfrifiadur i gychwyn."
    },
    "ar": {
      "term": "ذاكرة القراءة فقط (ROM)",
      "definition": "ذاكرة دائمة تحتوي على تعليمات لا يمكن تغييرها، مثل تعليمات بدء تشغيل الحاسوب."
    },
    "ro": {
      "term": "Memorie ROM",
      "definition": "Memorie permanentă care conține instrucțiuni care nu pot fi modificate, cum ar fi instrucțiunile de pornire a calculatorului."
    }
  }
}